xfab/__init__.py
xfab/atomlib.py
xfab/checks.py
xfab/detector.py
xfab/parameters.py
xfab/sg.py
xfab/sglib.py
xfab/structure.py
xfab/symmetry.py
xfab/tools.py
xfab/xfab_logging.py
xfab-0.0.6.data/scripts/findpeaks.py
xfab-0.0.6.data/scripts/flt_remove_beam.py
xfab-0.0.6.data/scripts/flt_split_phases.py
xfab-0.0.6.data/scripts/gff_to_ubi.py
xfab-0.0.6.data/scripts/grainspotter_loop.py
xfab-0.0.6.data/scripts/make_gve.py
xfab-0.0.6.data/scripts/makemap_all.py
xfab-0.0.6.data/scripts/plot_gff.py
xfab-0.0.6.data/scripts/tweakdetpars.py
xfab-0.0.6.data/scripts/ubi_to_gff.py
xfab-0.0.6.dist-info/LICENSE.txt
xfab-0.0.6.dist-info/METADATA
xfab-0.0.6.dist-info/WHEEL
xfab-0.0.6.dist-info/top_level.txt
xfab-0.0.6.dist-info/RECORD
