Metadata-Version: 2.1
Name: xfab
Version: 0.0.6
Summary: Crystallographic toolbox and library
Home-page: https://github.com/FABLE-3DXRD/xfab
Download-URL: http://sourceforge.net/project/showfiles.php?group_id=82044&package_id=309377
Maintainer: Henning Osholm Soerensen and Jon Wright
Maintainer-email: osholm@nano.ku.dk, wright@esrf.eu
License: GPL
Platform: UNKNOWN
License-File: LICENSE.txt
Requires-Dist: numpy
Requires-Dist: six
Requires-Dist: pycifrw
